three_merge/__init__.py
three_merge/merge.py
three_merge/tests/__init__.py
three_merge/tests/test_merge.py
three_merge-0.1.0.dist-info/LICENSE
three_merge-0.1.0.dist-info/METADATA
three_merge-0.1.0.dist-info/WHEEL
three_merge-0.1.0.dist-info/top_level.txt
three_merge-0.1.0.dist-info/RECORD
