Metadata-Version: 2.1
Name: three-merge
Version: 0.1.0
Summary: Simple library for merging two strings with respect to a base one
Home-page: https://github.com/spyder-ide/three-merge
Author: Spyder Project Contributors
Author-email: spyder.python@gmail.com
License: MIT
Keywords: Merge,Files,Three-way
Platform: UNKNOWN
Classifier: Development Status :: 4 - Beta
Classifier: Intended Audience :: Developers
Classifier: License :: OSI Approved :: MIT License
Classifier: Operating System :: MacOS
Classifier: Operating System :: Microsoft :: Windows
Classifier: Operating System :: POSIX :: Linux
Classifier: Programming Language :: Python :: 3.5
Classifier: Programming Language :: Python :: 3.6
Classifier: Programming Language :: Python :: 3.7
Classifier: Programming Language :: Python :: 3.8
Requires-Dist: diff-match-patch
Provides-Extra: test
Requires-Dist: pytest ; extra == 'test'
Requires-Dist: pytest-cov ; extra == 'test'
Requires-Dist: flaky ; extra == 'test'
Requires-Dist: pytest-timeout ; extra == 'test'
